speexaec/__init__.py
speexaec/_speexaec.c
speexaec/_speexaec.cpython-313-aarch64-linux-gnu.so
speexaec/_speexaec.pyx
speexaec/echo.pyx
speexaec/preprocess.pyx
speexaec/resample.pyx
speexaec.libs/libspeexdsp-7260fde4.so.1.5.2
speexaec-0.1.3.dist-info/METADATA
speexaec-0.1.3.dist-info/WHEEL
speexaec-0.1.3.dist-info/top_level.txt
speexaec-0.1.3.dist-info/RECORD
