Metadata-Version: 2.4
Name: speexaec
Version: 0.1.3
Summary: Python bindings for SpeexDSP audio processing library
Home-page: https://github.com/leitat-raise/package-speexaec
Author: J.David Luque
Author-email: jdluque@leitat.org
License: BSD-3-Clause
Project-URL: Source, https://github.com/leitat-raise/package-speexaec
Project-URL: Tracker, https://github.com/leitat-raise/package-speexaec/issues
Classifier: Development Status :: 3 - Alpha
Classifier: Intended Audience :: Developers
Classifier: License :: OSI Approved :: BSD License
Classifier: Programming Language :: Python
Classifier: Programming Language :: Python :: 3
Classifier: Programming Language :: Python :: 3 :: Only
Classifier: Programming Language :: Cython
Classifier: Topic :: Multimedia :: Sound/Audio :: Analysis
Classifier: Topic :: Software Development :: Libraries :: Python Modules
Requires-Python: >=3.9
Requires-Dist: numpy>=2
Dynamic: author
Dynamic: author-email
Dynamic: classifier
Dynamic: description
Dynamic: description-content-type
Dynamic: home-page
Dynamic: license
Dynamic: project-url
Dynamic: requires-dist
Dynamic: requires-python
Dynamic: summary
